antannotator/__init__.py
antannotator/annotation_controller.py
antannotator/persistence.py
antannotator/text_classification_wiget.py
antannotator/utils.py
antannotator-0.0.3.dist-info/LICENSE
antannotator-0.0.3.dist-info/METADATA
antannotator-0.0.3.dist-info/WHEEL
antannotator-0.0.3.dist-info/top_level.txt
antannotator-0.0.3.dist-info/RECORD
