Metadata-Version: 2.1
Name: antannotator
Version: 0.0.3
Summary: JupyterLab tool for data annotations for machine learning routines
Home-page: https://github.com/IvanAntipov/AntAnnotator
Author: Ivan Antipov
License: UNKNOWN
Platform: UNKNOWN
Classifier: Programming Language :: Python :: 3
Classifier: License :: OSI Approved :: MIT License
Classifier: Operating System :: OS Independent
Requires-Python: >=3.7
License-File: LICENSE
Requires-Dist: ipywidgets (>=7.6.3)
